{
    "aawiki": "php-1.31.0-wmf.23",
    "aawikibooks": "php-1.31.0-wmf.24",
    "aawiktionary": "php-1.31.0-wmf.24",
    "abwiki": "php-1.31.0-wmf.23",
    "abwiktionary": "php-1.31.0-wmf.24",
    "acewiki": "php-1.31.0-wmf.23",
    "advisorywiki": "php-1.31.0-wmf.24",
    "adywiki": "php-1.31.0-wmf.23",
    "afwiki": "php-1.31.0-wmf.23",
    "afwikibooks": "php-1.31.0-wmf.24",
    "afwikiquote": "php-1.31.0-wmf.24",
    "afwiktionary": "php-1.31.0-wmf.24",
    "akwiki": "php-1.31.0-wmf.23",
    "akwikibooks": "php-1.31.0-wmf.24",
    "akwiktionary": "php-1.31.0-wmf.24",
    "alswiki": "php-1.31.0-wmf.23",
    "amwiki": "php-1.31.0-wmf.23",
    "amwikimedia": "php-1.31.0-wmf.24",
    "amwikiquote": "php-1.31.0-wmf.24",
    "amwiktionary": "php-1.31.0-wmf.24",
    "angwiki": "php-1.31.0-wmf.23",
    "angwikibooks": "php-1.31.0-wmf.24",
    "angwikiquote": "php-1.31.0-wmf.24",
    "angwikisource": "php-1.31.0-wmf.24",
    "angwiktionary": "php-1.31.0-wmf.24",
    "anwiki": "php-1.31.0-wmf.23",
    "anwiktionary": "php-1.31.0-wmf.24",
    "arbcom_cswiki": "php-1.31.0-wmf.23",
    "arbcom_dewiki": "php-1.31.0-wmf.23",
    "arbcom_enwiki": "php-1.31.0-wmf.23",
    "arbcom_fiwiki": "php-1.31.0-wmf.23",
    "arbcom_nlwiki": "php-1.31.0-wmf.23",
    "arcwiki": "php-1.31.0-wmf.23",
    "arwiki": "php-1.31.0-wmf.23",
    "arwikibooks": "php-1.31.0-wmf.24",
    "arwikimedia": "php-1.31.0-wmf.24",
    "arwikinews": "php-1.31.0-wmf.24",
    "arwikiquote": "php-1.31.0-wmf.24",
    "arwikisource": "php-1.31.0-wmf.24",
    "arwikiversity": "php-1.31.0-wmf.24",
    "arwiktionary": "php-1.31.0-wmf.24",
    "arzwiki": "php-1.31.0-wmf.23",
    "astwiki": "php-1.31.0-wmf.23",
    "astwikibooks": "php-1.31.0-wmf.24",
    "astwikiquote": "php-1.31.0-wmf.24",
    "astwiktionary": "php-1.31.0-wmf.24",
    "aswiki": "php-1.31.0-wmf.23",
    "aswikibooks": "php-1.31.0-wmf.24",
    "aswikisource": "php-1.31.0-wmf.24",
    "aswiktionary": "php-1.31.0-wmf.24",
    "atjwiki": "php-1.31.0-wmf.23",
    "auditcomwiki": "php-1.31.0-wmf.24",
    "avwiki": "php-1.31.0-wmf.23",
    "avwiktionary": "php-1.31.0-wmf.24",
    "aywiki": "php-1.31.0-wmf.23",
    "aywikibooks": "php-1.31.0-wmf.24",
    "aywiktionary": "php-1.31.0-wmf.24",
    "azbwiki": "php-1.31.0-wmf.23",
    "azwiki": "php-1.31.0-wmf.23",
    "azwikibooks": "php-1.31.0-wmf.24",
    "azwikiquote": "php-1.31.0-wmf.24",
    "azwikisource": "php-1.31.0-wmf.24",
    "azwiktionary": "php-1.31.0-wmf.24",
    "barwiki": "php-1.31.0-wmf.23",
    "bat_smgwiki": "php-1.31.0-wmf.23",
    "bawiki": "php-1.31.0-wmf.23",
    "bawikibooks": "php-1.31.0-wmf.24",
    "bclwiki": "php-1.31.0-wmf.23",
    "bdwikimedia": "php-1.31.0-wmf.24",
    "be_x_oldwiki": "php-1.31.0-wmf.23",
    "betawikiversity": "php-1.31.0-wmf.24",
    "bewiki": "php-1.31.0-wmf.23",
    "bewikibooks": "php-1.31.0-wmf.24",
    "bewikimedia": "php-1.31.0-wmf.24",
    "bewikiquote": "php-1.31.0-wmf.24",
    "bewikisource": "php-1.31.0-wmf.24",
    "bewiktionary": "php-1.31.0-wmf.24",
    "bgwiki": "php-1.31.0-wmf.23",
    "bgwikibooks": "php-1.31.0-wmf.24",
    "bgwikinews": "php-1.31.0-wmf.24",
    "bgwikiquote": "php-1.31.0-wmf.24",
    "bgwikisource": "php-1.31.0-wmf.24",
    "bgwiktionary": "php-1.31.0-wmf.24",
    "bhwiki": "php-1.31.0-wmf.23",
    "bhwiktionary": "php-1.31.0-wmf.24",
    "biwiki": "php-1.31.0-wmf.23",
    "biwikibooks": "php-1.31.0-wmf.24",
    "biwiktionary": "php-1.31.0-wmf.24",
    "bjnwiki": "php-1.31.0-wmf.23",
    "bmwiki": "php-1.31.0-wmf.23",
    "bmwikibooks": "php-1.31.0-wmf.24",
    "bmwikiquote": "php-1.31.0-wmf.24",
    "bmwiktionary": "php-1.31.0-wmf.24",
    "bnwiki": "php-1.31.0-wmf.23",
    "bnwikibooks": "php-1.31.0-wmf.24",
    "bnwikisource": "php-1.31.0-wmf.24",
    "bnwiktionary": "php-1.31.0-wmf.24",
    "boardgovcomwiki": "php-1.31.0-wmf.24",
    "boardwiki": "php-1.31.0-wmf.24",
    "bowiki": "php-1.31.0-wmf.23",
    "bowikibooks": "php-1.31.0-wmf.24",
    "bowiktionary": "php-1.31.0-wmf.24",
    "bpywiki": "php-1.31.0-wmf.23",
    "brwiki": "php-1.31.0-wmf.23",
    "brwikimedia": "php-1.31.0-wmf.24",
    "brwikiquote": "php-1.31.0-wmf.24",
    "brwikisource": "php-1.31.0-wmf.24",
    "brwiktionary": "php-1.31.0-wmf.24",
    "bswiki": "php-1.31.0-wmf.23",
    "bswikibooks": "php-1.31.0-wmf.24",
    "bswikinews": "php-1.31.0-wmf.24",
    "bswikiquote": "php-1.31.0-wmf.24",
    "bswikisource": "php-1.31.0-wmf.24",
    "bswiktionary": "php-1.31.0-wmf.24",
    "bugwiki": "php-1.31.0-wmf.23",
    "bxrwiki": "php-1.31.0-wmf.23",
    "cawiki": "php-1.31.0-wmf.24",
    "cawikibooks": "php-1.31.0-wmf.24",
    "cawikimedia": "php-1.31.0-wmf.24",
    "cawikinews": "php-1.31.0-wmf.24",
    "cawikiquote": "php-1.31.0-wmf.24",
    "cawikisource": "php-1.31.0-wmf.24",
    "cawiktionary": "php-1.31.0-wmf.24",
    "cbk_zamwiki": "php-1.31.0-wmf.23",
    "cdowiki": "php-1.31.0-wmf.23",
    "cebwiki": "php-1.31.0-wmf.23",
    "cewiki": "php-1.31.0-wmf.23",
    "chairwiki": "php-1.31.0-wmf.24",
    "chapcomwiki": "php-1.31.0-wmf.24",
    "checkuserwiki": "php-1.31.0-wmf.24",
    "chowiki": "php-1.31.0-wmf.24",
    "chrwiki": "php-1.31.0-wmf.23",
    "chrwiktionary": "php-1.31.0-wmf.24",
    "chwiki": "php-1.31.0-wmf.23",
    "chwikibooks": "php-1.31.0-wmf.24",
    "chwiktionary": "php-1.31.0-wmf.24",
    "chywiki": "php-1.31.0-wmf.23",
    "ckbwiki": "php-1.31.0-wmf.23",
    "cnwikimedia": "php-1.31.0-wmf.24",
    "collabwiki": "php-1.31.0-wmf.24",
    "commonswiki": "php-1.31.0-wmf.24",
    "cowiki": "php-1.31.0-wmf.23",
    "cowikibooks": "php-1.31.0-wmf.24",
    "cowikimedia": "php-1.31.0-wmf.24",
    "cowikiquote": "php-1.31.0-wmf.24",
    "cowiktionary": "php-1.31.0-wmf.24",
    "crhwiki": "php-1.31.0-wmf.23",
    "crwiki": "php-1.31.0-wmf.23",
    "crwikiquote": "php-1.31.0-wmf.24",
    "crwiktionary": "php-1.31.0-wmf.24",
    "csbwiki": "php-1.31.0-wmf.23",
    "csbwiktionary": "php-1.31.0-wmf.24",
    "cswiki": "php-1.31.0-wmf.23",
    "cswikibooks": "php-1.31.0-wmf.24",
    "cswikinews": "php-1.31.0-wmf.24",
    "cswikiquote": "php-1.31.0-wmf.24",
    "cswikisource": "php-1.31.0-wmf.24",
    "cswikiversity": "php-1.31.0-wmf.24",
    "cswiktionary": "php-1.31.0-wmf.24",
    "cuwiki": "php-1.31.0-wmf.23",
    "cvwiki": "php-1.31.0-wmf.23",
    "cvwikibooks": "php-1.31.0-wmf.24",
    "cywiki": "php-1.31.0-wmf.23",
    "cywikibooks": "php-1.31.0-wmf.24",
    "cywikiquote": "php-1.31.0-wmf.24",
    "cywikisource": "php-1.31.0-wmf.24",
    "cywiktionary": "php-1.31.0-wmf.24",
    "dawiki": "php-1.31.0-wmf.23",
    "dawikibooks": "php-1.31.0-wmf.24",
    "dawikiquote": "php-1.31.0-wmf.24",
    "dawikisource": "php-1.31.0-wmf.24",
    "dawiktionary": "php-1.31.0-wmf.24",
    "dewiki": "php-1.31.0-wmf.23",
    "dewikibooks": "php-1.31.0-wmf.24",
    "dewikinews": "php-1.31.0-wmf.24",
    "dewikiquote": "php-1.31.0-wmf.24",
    "dewikisource": "php-1.31.0-wmf.24",
    "dewikiversity": "php-1.31.0-wmf.24",
    "dewikivoyage": "php-1.31.0-wmf.24",
    "dewiktionary": "php-1.31.0-wmf.24",
    "dinwiki": "php-1.31.0-wmf.23",
    "diqwiki": "php-1.31.0-wmf.23",
    "dkwikimedia": "php-1.31.0-wmf.24",
    "donatewiki": "php-1.31.0-wmf.24",
    "dsbwiki": "php-1.31.0-wmf.23",
    "dtywiki": "php-1.31.0-wmf.23",
    "dvwiki": "php-1.31.0-wmf.23",
    "dvwiktionary": "php-1.31.0-wmf.24",
    "dzwiki": "php-1.31.0-wmf.23",
    "dzwiktionary": "php-1.31.0-wmf.24",
    "ecwikimedia": "php-1.31.0-wmf.24",
    "eewiki": "php-1.31.0-wmf.23",
    "electcomwiki": "php-1.31.0-wmf.24",
    "elwiki": "php-1.31.0-wmf.23",
    "elwikibooks": "php-1.31.0-wmf.24",
    "elwikinews": "php-1.31.0-wmf.24",
    "elwikiquote": "php-1.31.0-wmf.24",
    "elwikisource": "php-1.31.0-wmf.24",
    "elwikiversity": "php-1.31.0-wmf.24",
    "elwikivoyage": "php-1.31.0-wmf.24",
    "elwiktionary": "php-1.31.0-wmf.24",
    "emlwiki": "php-1.31.0-wmf.23",
    "enwiki": "php-1.31.0-wmf.23",
    "enwikibooks": "php-1.31.0-wmf.24",
    "enwikinews": "php-1.31.0-wmf.24",
    "enwikiquote": "php-1.31.0-wmf.24",
    "enwikisource": "php-1.31.0-wmf.24",
    "enwikiversity": "php-1.31.0-wmf.24",
    "enwikivoyage": "php-1.31.0-wmf.24",
    "enwiktionary": "php-1.31.0-wmf.24",
    "eowiki": "php-1.31.0-wmf.23",
    "eowikibooks": "php-1.31.0-wmf.24",
    "eowikinews": "php-1.31.0-wmf.24",
    "eowikiquote": "php-1.31.0-wmf.24",
    "eowikisource": "php-1.31.0-wmf.24",
    "eowiktionary": "php-1.31.0-wmf.24",
    "eswiki": "php-1.31.0-wmf.23",
    "eswikibooks": "php-1.31.0-wmf.24",
    "eswikinews": "php-1.31.0-wmf.24",
    "eswikiquote": "php-1.31.0-wmf.24",
    "eswikisource": "php-1.31.0-wmf.24",
    "eswikiversity": "php-1.31.0-wmf.24",
    "eswikivoyage": "php-1.31.0-wmf.24",
    "eswiktionary": "php-1.31.0-wmf.24",
    "etwiki": "php-1.31.0-wmf.23",
    "etwikibooks": "php-1.31.0-wmf.24",
    "etwikimedia": "php-1.31.0-wmf.24",
    "etwikiquote": "php-1.31.0-wmf.24",
    "etwikisource": "php-1.31.0-wmf.24",
    "etwiktionary": "php-1.31.0-wmf.24",
    "euwiki": "php-1.31.0-wmf.23",
    "euwikibooks": "php-1.31.0-wmf.24",
    "euwikiquote": "php-1.31.0-wmf.24",
    "euwiktionary": "php-1.31.0-wmf.24",
    "execwiki": "php-1.31.0-wmf.24",
    "extwiki": "php-1.31.0-wmf.23",
    "fawiki": "php-1.31.0-wmf.23",
    "fawikibooks": "php-1.31.0-wmf.24",
    "fawikinews": "php-1.31.0-wmf.24",
    "fawikiquote": "php-1.31.0-wmf.24",
    "fawikisource": "php-1.31.0-wmf.24",
    "fawikivoyage": "php-1.31.0-wmf.24",
    "fawiktionary": "php-1.31.0-wmf.24",
    "fdcwiki": "php-1.31.0-wmf.24",
    "ffwiki": "php-1.31.0-wmf.23",
    "fiu_vrowiki": "php-1.31.0-wmf.23",
    "fiwiki": "php-1.31.0-wmf.23",
    "fiwikibooks": "php-1.31.0-wmf.24",
    "fiwikimedia": "php-1.31.0-wmf.24",
    "fiwikinews": "php-1.31.0-wmf.24",
    "fiwikiquote": "php-1.31.0-wmf.24",
    "fiwikisource": "php-1.31.0-wmf.24",
    "fiwikiversity": "php-1.31.0-wmf.24",
    "fiwikivoyage": "php-1.31.0-wmf.24",
    "fiwiktionary": "php-1.31.0-wmf.24",
    "fjwiki": "php-1.31.0-wmf.23",
    "fjwiktionary": "php-1.31.0-wmf.24",
    "foundationwiki": "php-1.31.0-wmf.24",
    "fowiki": "php-1.31.0-wmf.23",
    "fowikisource": "php-1.31.0-wmf.24",
    "fowiktionary": "php-1.31.0-wmf.24",
    "frpwiki": "php-1.31.0-wmf.23",
    "frrwiki": "php-1.31.0-wmf.23",
    "frwiki": "php-1.31.0-wmf.23",
    "frwikibooks": "php-1.31.0-wmf.24",
    "frwikinews": "php-1.31.0-wmf.24",
    "frwikiquote": "php-1.31.0-wmf.24",
    "frwikisource": "php-1.31.0-wmf.24",
    "frwikiversity": "php-1.31.0-wmf.24",
    "frwikivoyage": "php-1.31.0-wmf.24",
    "frwiktionary": "php-1.31.0-wmf.24",
    "furwiki": "php-1.31.0-wmf.23",
    "fywiki": "php-1.31.0-wmf.23",
    "fywikibooks": "php-1.31.0-wmf.24",
    "fywiktionary": "php-1.31.0-wmf.24",
    "gagwiki": "php-1.31.0-wmf.23",
    "ganwiki": "php-1.31.0-wmf.23",
    "gawiki": "php-1.31.0-wmf.23",
    "gawikibooks": "php-1.31.0-wmf.24",
    "gawikiquote": "php-1.31.0-wmf.24",
    "gawiktionary": "php-1.31.0-wmf.24",
    "gdwiki": "php-1.31.0-wmf.23",
    "gdwiktionary": "php-1.31.0-wmf.24",
    "glkwiki": "php-1.31.0-wmf.23",
    "glwiki": "php-1.31.0-wmf.23",
    "glwikibooks": "php-1.31.0-wmf.24",
    "glwikiquote": "php-1.31.0-wmf.24",
    "glwikisource": "php-1.31.0-wmf.24",
    "glwiktionary": "php-1.31.0-wmf.24",
    "gnwiki": "php-1.31.0-wmf.23",
    "gnwikibooks": "php-1.31.0-wmf.24",
    "gnwiktionary": "php-1.31.0-wmf.24",
    "gomwiki": "php-1.31.0-wmf.23",
    "gotwiki": "php-1.31.0-wmf.23",
    "gotwikibooks": "php-1.31.0-wmf.24",
    "grantswiki": "php-1.31.0-wmf.24",
    "guwiki": "php-1.31.0-wmf.23",
    "guwikibooks": "php-1.31.0-wmf.24",
    "guwikiquote": "php-1.31.0-wmf.24",
    "guwikisource": "php-1.31.0-wmf.24",
    "guwiktionary": "php-1.31.0-wmf.24",
    "gvwiki": "php-1.31.0-wmf.23",
    "gvwiktionary": "php-1.31.0-wmf.24",
    "hakwiki": "php-1.31.0-wmf.23",
    "hawiki": "php-1.31.0-wmf.23",
    "hawiktionary": "php-1.31.0-wmf.24",
    "hawwiki": "php-1.31.0-wmf.23",
    "hewiki": "php-1.31.0-wmf.24",
    "hewikibooks": "php-1.31.0-wmf.24",
    "hewikinews": "php-1.31.0-wmf.24",
    "hewikiquote": "php-1.31.0-wmf.24",
    "hewikisource": "php-1.31.0-wmf.24",
    "hewikivoyage": "php-1.31.0-wmf.24",
    "hewiktionary": "php-1.31.0-wmf.24",
    "hifwiki": "php-1.31.0-wmf.23",
    "hifwiktionary": "php-1.31.0-wmf.24",
    "hiwiki": "php-1.31.0-wmf.23",
    "hiwikibooks": "php-1.31.0-wmf.24",
    "hiwikiquote": "php-1.31.0-wmf.24",
    "hiwikiversity": "php-1.31.0-wmf.24",
    "hiwikivoyage": "php-1.31.0-wmf.24",
    "hiwiktionary": "php-1.31.0-wmf.24",
    "howiki": "php-1.31.0-wmf.24",
    "hrwiki": "php-1.31.0-wmf.23",
    "hrwikibooks": "php-1.31.0-wmf.24",
    "hrwikiquote": "php-1.31.0-wmf.24",
    "hrwikisource": "php-1.31.0-wmf.24",
    "hrwiktionary": "php-1.31.0-wmf.24",
    "hsbwiki": "php-1.31.0-wmf.23",
    "hsbwiktionary": "php-1.31.0-wmf.24",
    "htwiki": "php-1.31.0-wmf.23",
    "htwikisource": "php-1.31.0-wmf.24",
    "huwiki": "php-1.31.0-wmf.23",
    "huwikibooks": "php-1.31.0-wmf.24",
    "huwikinews": "php-1.31.0-wmf.24",
    "huwikiquote": "php-1.31.0-wmf.24",
    "huwikisource": "php-1.31.0-wmf.24",
    "huwiktionary": "php-1.31.0-wmf.24",
    "hywiki": "php-1.31.0-wmf.23",
    "hywikibooks": "php-1.31.0-wmf.24",
    "hywikiquote": "php-1.31.0-wmf.24",
    "hywikisource": "php-1.31.0-wmf.24",
    "hywiktionary": "php-1.31.0-wmf.24",
    "hzwiki": "php-1.31.0-wmf.24",
    "iawiki": "php-1.31.0-wmf.23",
    "iawikibooks": "php-1.31.0-wmf.24",
    "iawiktionary": "php-1.31.0-wmf.24",
    "idwiki": "php-1.31.0-wmf.23",
    "idwikibooks": "php-1.31.0-wmf.24",
    "idwikiquote": "php-1.31.0-wmf.24",
    "idwikisource": "php-1.31.0-wmf.24",
    "idwiktionary": "php-1.31.0-wmf.24",
    "iegcomwiki": "php-1.31.0-wmf.24",
    "iewiki": "php-1.31.0-wmf.23",
    "iewikibooks": "php-1.31.0-wmf.24",
    "iewiktionary": "php-1.31.0-wmf.24",
    "igwiki": "php-1.31.0-wmf.23",
    "iiwiki": "php-1.31.0-wmf.24",
    "ikwiki": "php-1.31.0-wmf.23",
    "ikwiktionary": "php-1.31.0-wmf.24",
    "ilowiki": "php-1.31.0-wmf.23",
    "ilwikimedia": "php-1.31.0-wmf.24",
    "incubatorwiki": "php-1.31.0-wmf.24",
    "internalwiki": "php-1.31.0-wmf.24",
    "iowiki": "php-1.31.0-wmf.23",
    "iowiktionary": "php-1.31.0-wmf.24",
    "iswiki": "php-1.31.0-wmf.23",
    "iswikibooks": "php-1.31.0-wmf.24",
    "iswikiquote": "php-1.31.0-wmf.24",
    "iswikisource": "php-1.31.0-wmf.24",
    "iswiktionary": "php-1.31.0-wmf.24",
    "itwiki": "php-1.31.0-wmf.23",
    "itwikibooks": "php-1.31.0-wmf.24",
    "itwikinews": "php-1.31.0-wmf.24",
    "itwikiquote": "php-1.31.0-wmf.24",
    "itwikisource": "php-1.31.0-wmf.24",
    "itwikiversity": "php-1.31.0-wmf.24",
    "itwikivoyage": "php-1.31.0-wmf.24",
    "itwiktionary": "php-1.31.0-wmf.24",
    "iuwiki": "php-1.31.0-wmf.23",
    "iuwiktionary": "php-1.31.0-wmf.24",
    "jamwiki": "php-1.31.0-wmf.23",
    "jawiki": "php-1.31.0-wmf.23",
    "jawikibooks": "php-1.31.0-wmf.24",
    "jawikinews": "php-1.31.0-wmf.24",
    "jawikiquote": "php-1.31.0-wmf.24",
    "jawikisource": "php-1.31.0-wmf.24",
    "jawikiversity": "php-1.31.0-wmf.24",
    "jawiktionary": "php-1.31.0-wmf.24",
    "jbowiki": "php-1.31.0-wmf.23",
    "jbowiktionary": "php-1.31.0-wmf.24",
    "jvwiki": "php-1.31.0-wmf.23",
    "jvwiktionary": "php-1.31.0-wmf.24",
    "kaawiki": "php-1.31.0-wmf.23",
    "kabwiki": "php-1.31.0-wmf.23",
    "kawiki": "php-1.31.0-wmf.23",
    "kawikibooks": "php-1.31.0-wmf.24",
    "kawikiquote": "php-1.31.0-wmf.24",
    "kawiktionary": "php-1.31.0-wmf.24",
    "kbdwiki": "php-1.31.0-wmf.23",
    "kbpwiki": "php-1.31.0-wmf.23",
    "kgwiki": "php-1.31.0-wmf.23",
    "kiwiki": "php-1.31.0-wmf.23",
    "kjwiki": "php-1.31.0-wmf.24",
    "kkwiki": "php-1.31.0-wmf.23",
    "kkwikibooks": "php-1.31.0-wmf.24",
    "kkwikiquote": "php-1.31.0-wmf.24",
    "kkwiktionary": "php-1.31.0-wmf.24",
    "klwiki": "php-1.31.0-wmf.23",
    "klwiktionary": "php-1.31.0-wmf.24",
    "kmwiki": "php-1.31.0-wmf.23",
    "kmwikibooks": "php-1.31.0-wmf.24",
    "kmwiktionary": "php-1.31.0-wmf.24",
    "knwiki": "php-1.31.0-wmf.23",
    "knwikibooks": "php-1.31.0-wmf.24",
    "knwikiquote": "php-1.31.0-wmf.24",
    "knwikisource": "php-1.31.0-wmf.24",
    "knwiktionary": "php-1.31.0-wmf.24",
    "koiwiki": "php-1.31.0-wmf.23",
    "kowiki": "php-1.31.0-wmf.23",
    "kowikibooks": "php-1.31.0-wmf.24",
    "kowikinews": "php-1.31.0-wmf.24",
    "kowikiquote": "php-1.31.0-wmf.24",
    "kowikisource": "php-1.31.0-wmf.24",
    "kowikiversity": "php-1.31.0-wmf.24",
    "kowiktionary": "php-1.31.0-wmf.24",
    "krcwiki": "php-1.31.0-wmf.23",
    "krwiki": "php-1.31.0-wmf.24",
    "krwikiquote": "php-1.31.0-wmf.24",
    "kshwiki": "php-1.31.0-wmf.23",
    "kswiki": "php-1.31.0-wmf.23",
    "kswikibooks": "php-1.31.0-wmf.24",
    "kswikiquote": "php-1.31.0-wmf.24",
    "kswiktionary": "php-1.31.0-wmf.24",
    "kuwiki": "php-1.31.0-wmf.23",
    "kuwikibooks": "php-1.31.0-wmf.24",
    "kuwikiquote": "php-1.31.0-wmf.24",
    "kuwiktionary": "php-1.31.0-wmf.24",
    "kvwiki": "php-1.31.0-wmf.23",
    "kwwiki": "php-1.31.0-wmf.23",
    "kwwikiquote": "php-1.31.0-wmf.24",
    "kwwiktionary": "php-1.31.0-wmf.24",
    "kywiki": "php-1.31.0-wmf.23",
    "kywikibooks": "php-1.31.0-wmf.24",
    "kywikiquote": "php-1.31.0-wmf.24",
    "kywiktionary": "php-1.31.0-wmf.24",
    "labswiki": "php-1.31.0-wmf.24",
    "labtestwiki": "php-1.31.0-wmf.24",
    "ladwiki": "php-1.31.0-wmf.23",
    "lawiki": "php-1.31.0-wmf.23",
    "lawikibooks": "php-1.31.0-wmf.24",
    "lawikiquote": "php-1.31.0-wmf.24",
    "lawikisource": "php-1.31.0-wmf.24",
    "lawiktionary": "php-1.31.0-wmf.24",
    "lbewiki": "php-1.31.0-wmf.23",
    "lbwiki": "php-1.31.0-wmf.23",
    "lbwikibooks": "php-1.31.0-wmf.24",
    "lbwikiquote": "php-1.31.0-wmf.24",
    "lbwiktionary": "php-1.31.0-wmf.24",
    "legalteamwiki": "php-1.31.0-wmf.24",
    "lezwiki": "php-1.31.0-wmf.23",
    "lgwiki": "php-1.31.0-wmf.23",
    "lijwiki": "php-1.31.0-wmf.23",
    "liwiki": "php-1.31.0-wmf.23",
    "liwikibooks": "php-1.31.0-wmf.24",
    "liwikiquote": "php-1.31.0-wmf.24",
    "liwikisource": "php-1.31.0-wmf.24",
    "liwiktionary": "php-1.31.0-wmf.24",
    "lmowiki": "php-1.31.0-wmf.23",
    "lnwiki": "php-1.31.0-wmf.23",
    "lnwikibooks": "php-1.31.0-wmf.24",
    "lnwiktionary": "php-1.31.0-wmf.24",
    "loginwiki": "php-1.31.0-wmf.24",
    "lowiki": "php-1.31.0-wmf.23",
    "lowiktionary": "php-1.31.0-wmf.24",
    "lrcwiki": "php-1.31.0-wmf.23",
    "ltgwiki": "php-1.31.0-wmf.23",
    "ltwiki": "php-1.31.0-wmf.23",
    "ltwikibooks": "php-1.31.0-wmf.24",
    "ltwikiquote": "php-1.31.0-wmf.24",
    "ltwikisource": "php-1.31.0-wmf.24",
    "ltwiktionary": "php-1.31.0-wmf.24",
    "lvwiki": "php-1.31.0-wmf.23",
    "lvwikibooks": "php-1.31.0-wmf.24",
    "lvwiktionary": "php-1.31.0-wmf.24",
    "maiwiki": "php-1.31.0-wmf.23",
    "maiwikimedia": "php-1.31.0-wmf.24",
    "map_bmswiki": "php-1.31.0-wmf.23",
    "mdfwiki": "php-1.31.0-wmf.23",
    "mediawikiwiki": "php-1.31.0-wmf.24",
    "metawiki": "php-1.31.0-wmf.24",
    "mgwiki": "php-1.31.0-wmf.23",
    "mgwikibooks": "php-1.31.0-wmf.24",
    "mgwiktionary": "php-1.31.0-wmf.24",
    "mhrwiki": "php-1.31.0-wmf.23",
    "mhwiki": "php-1.31.0-wmf.24",
    "mhwiktionary": "php-1.31.0-wmf.24",
    "minwiki": "php-1.31.0-wmf.23",
    "miwiki": "php-1.31.0-wmf.23",
    "miwikibooks": "php-1.31.0-wmf.24",
    "miwiktionary": "php-1.31.0-wmf.24",
    "mkwiki": "php-1.31.0-wmf.23",
    "mkwikibooks": "php-1.31.0-wmf.24",
    "mkwikimedia": "php-1.31.0-wmf.24",
    "mkwikisource": "php-1.31.0-wmf.24",
    "mkwiktionary": "php-1.31.0-wmf.24",
    "mlwiki": "php-1.31.0-wmf.23",
    "mlwikibooks": "php-1.31.0-wmf.24",
    "mlwikiquote": "php-1.31.0-wmf.24",
    "mlwikisource": "php-1.31.0-wmf.24",
    "mlwiktionary": "php-1.31.0-wmf.24",
    "mnwiki": "php-1.31.0-wmf.23",
    "mnwikibooks": "php-1.31.0-wmf.24",
    "mnwiktionary": "php-1.31.0-wmf.24",
    "movementroleswiki": "php-1.31.0-wmf.24",
    "mrjwiki": "php-1.31.0-wmf.23",
    "mrwiki": "php-1.31.0-wmf.23",
    "mrwikibooks": "php-1.31.0-wmf.24",
    "mrwikiquote": "php-1.31.0-wmf.24",
    "mrwikisource": "php-1.31.0-wmf.24",
    "mrwiktionary": "php-1.31.0-wmf.24",
    "mswiki": "php-1.31.0-wmf.23",
    "mswikibooks": "php-1.31.0-wmf.24",
    "mswiktionary": "php-1.31.0-wmf.24",
    "mtwiki": "php-1.31.0-wmf.23",
    "mtwiktionary": "php-1.31.0-wmf.24",
    "muswiki": "php-1.31.0-wmf.24",
    "mwlwiki": "php-1.31.0-wmf.23",
    "mxwikimedia": "php-1.31.0-wmf.24",
    "myvwiki": "php-1.31.0-wmf.23",
    "mywiki": "php-1.31.0-wmf.23",
    "mywikibooks": "php-1.31.0-wmf.24",
    "mywiktionary": "php-1.31.0-wmf.24",
    "mznwiki": "php-1.31.0-wmf.23",
    "nahwiki": "php-1.31.0-wmf.23",
    "nahwikibooks": "php-1.31.0-wmf.24",
    "nahwiktionary": "php-1.31.0-wmf.24",
    "napwiki": "php-1.31.0-wmf.23",
    "nawiki": "php-1.31.0-wmf.23",
    "nawikibooks": "php-1.31.0-wmf.24",
    "nawikiquote": "php-1.31.0-wmf.24",
    "nawiktionary": "php-1.31.0-wmf.24",
    "nds_nlwiki": "php-1.31.0-wmf.23",
    "ndswiki": "php-1.31.0-wmf.23",
    "ndswikibooks": "php-1.31.0-wmf.24",
    "ndswikiquote": "php-1.31.0-wmf.24",
    "ndswiktionary": "php-1.31.0-wmf.24",
    "newiki": "php-1.31.0-wmf.23",
    "newikibooks": "php-1.31.0-wmf.24",
    "newiktionary": "php-1.31.0-wmf.24",
    "newwiki": "php-1.31.0-wmf.23",
    "ngwiki": "php-1.31.0-wmf.24",
    "nlwiki": "php-1.31.0-wmf.23",
    "nlwikibooks": "php-1.31.0-wmf.24",
    "nlwikimedia": "php-1.31.0-wmf.24",
    "nlwikinews": "php-1.31.0-wmf.24",
    "nlwikiquote": "php-1.31.0-wmf.24",
    "nlwikisource": "php-1.31.0-wmf.24",
    "nlwikivoyage": "php-1.31.0-wmf.24",
    "nlwiktionary": "php-1.31.0-wmf.24",
    "nnwiki": "php-1.31.0-wmf.23",
    "nnwikiquote": "php-1.31.0-wmf.24",
    "nnwiktionary": "php-1.31.0-wmf.24",
    "noboard_chapterswikimedia": "php-1.31.0-wmf.24",
    "nostalgiawiki": "php-1.31.0-wmf.24",
    "novwiki": "php-1.31.0-wmf.23",
    "nowiki": "php-1.31.0-wmf.23",
    "nowikibooks": "php-1.31.0-wmf.24",
    "nowikimedia": "php-1.31.0-wmf.24",
    "nowikinews": "php-1.31.0-wmf.24",
    "nowikiquote": "php-1.31.0-wmf.24",
    "nowikisource": "php-1.31.0-wmf.24",
    "nowiktionary": "php-1.31.0-wmf.24",
    "nrmwiki": "php-1.31.0-wmf.23",
    "nsowiki": "php-1.31.0-wmf.23",
    "nvwiki": "php-1.31.0-wmf.23",
    "nycwikimedia": "php-1.31.0-wmf.24",
    "nywiki": "php-1.31.0-wmf.23",
    "nzwikimedia": "php-1.31.0-wmf.24",
    "ocwiki": "php-1.31.0-wmf.23",
    "ocwikibooks": "php-1.31.0-wmf.24",
    "ocwiktionary": "php-1.31.0-wmf.24",
    "officewiki": "php-1.31.0-wmf.24",
    "olowiki": "php-1.31.0-wmf.23",
    "ombudsmenwiki": "php-1.31.0-wmf.24",
    "omwiki": "php-1.31.0-wmf.23",
    "omwiktionary": "php-1.31.0-wmf.24",
    "orwiki": "php-1.31.0-wmf.23",
    "orwikisource": "php-1.31.0-wmf.24",
    "orwiktionary": "php-1.31.0-wmf.24",
    "oswiki": "php-1.31.0-wmf.23",
    "otrs_wikiwiki": "php-1.31.0-wmf.24",
    "outreachwiki": "php-1.31.0-wmf.24",
    "pa_uswikimedia": "php-1.31.0-wmf.24",
    "pagwiki": "php-1.31.0-wmf.23",
    "pamwiki": "php-1.31.0-wmf.23",
    "papwiki": "php-1.31.0-wmf.23",
    "pawiki": "php-1.31.0-wmf.23",
    "pawikibooks": "php-1.31.0-wmf.24",
    "pawikisource": "php-1.31.0-wmf.24",
    "pawiktionary": "php-1.31.0-wmf.24",
    "pcdwiki": "php-1.31.0-wmf.23",
    "pdcwiki": "php-1.31.0-wmf.23",
    "pflwiki": "php-1.31.0-wmf.23",
    "pihwiki": "php-1.31.0-wmf.23",
    "piwiki": "php-1.31.0-wmf.23",
    "piwiktionary": "php-1.31.0-wmf.24",
    "plwiki": "php-1.31.0-wmf.23",
    "plwikibooks": "php-1.31.0-wmf.24",
    "plwikimedia": "php-1.31.0-wmf.24",
    "plwikinews": "php-1.31.0-wmf.24",
    "plwikiquote": "php-1.31.0-wmf.24",
    "plwikisource": "php-1.31.0-wmf.24",
    "plwikivoyage": "php-1.31.0-wmf.24",
    "plwiktionary": "php-1.31.0-wmf.24",
    "pmswiki": "php-1.31.0-wmf.23",
    "pnbwiki": "php-1.31.0-wmf.23",
    "pnbwiktionary": "php-1.31.0-wmf.24",
    "pntwiki": "php-1.31.0-wmf.23",
    "projectcomwiki": "php-1.31.0-wmf.24",
    "pswiki": "php-1.31.0-wmf.23",
    "pswikibooks": "php-1.31.0-wmf.24",
    "pswiktionary": "php-1.31.0-wmf.24",
    "ptwiki": "php-1.31.0-wmf.23",
    "ptwikibooks": "php-1.31.0-wmf.24",
    "ptwikimedia": "php-1.31.0-wmf.24",
    "ptwikinews": "php-1.31.0-wmf.24",
    "ptwikiquote": "php-1.31.0-wmf.24",
    "ptwikisource": "php-1.31.0-wmf.24",
    "ptwikiversity": "php-1.31.0-wmf.24",
    "ptwikivoyage": "php-1.31.0-wmf.24",
    "ptwiktionary": "php-1.31.0-wmf.24",
    "qualitywiki": "php-1.31.0-wmf.24",
    "quwiki": "php-1.31.0-wmf.23",
    "quwikibooks": "php-1.31.0-wmf.24",
    "quwikiquote": "php-1.31.0-wmf.24",
    "quwiktionary": "php-1.31.0-wmf.24",
    "rmwiki": "php-1.31.0-wmf.23",
    "rmwikibooks": "php-1.31.0-wmf.24",
    "rmwiktionary": "php-1.31.0-wmf.24",
    "rmywiki": "php-1.31.0-wmf.23",
    "rnwiki": "php-1.31.0-wmf.23",
    "rnwiktionary": "php-1.31.0-wmf.24",
    "roa_rupwiki": "php-1.31.0-wmf.23",
    "roa_rupwiktionary": "php-1.31.0-wmf.24",
    "roa_tarawiki": "php-1.31.0-wmf.23",
    "rowiki": "php-1.31.0-wmf.23",
    "rowikibooks": "php-1.31.0-wmf.24",
    "rowikinews": "php-1.31.0-wmf.24",
    "rowikiquote": "php-1.31.0-wmf.24",
    "rowikisource": "php-1.31.0-wmf.24",
    "rowikivoyage": "php-1.31.0-wmf.24",
    "rowiktionary": "php-1.31.0-wmf.24",
    "rswikimedia": "php-1.31.0-wmf.24",
    "ruewiki": "php-1.31.0-wmf.23",
    "ruwiki": "php-1.31.0-wmf.23",
    "ruwikibooks": "php-1.31.0-wmf.24",
    "ruwikimedia": "php-1.31.0-wmf.24",
    "ruwikinews": "php-1.31.0-wmf.24",
    "ruwikiquote": "php-1.31.0-wmf.24",
    "ruwikisource": "php-1.31.0-wmf.24",
    "ruwikiversity": "php-1.31.0-wmf.24",
    "ruwikivoyage": "php-1.31.0-wmf.24",
    "ruwiktionary": "php-1.31.0-wmf.24",
    "rwwiki": "php-1.31.0-wmf.23",
    "rwwiktionary": "php-1.31.0-wmf.24",
    "sahwiki": "php-1.31.0-wmf.23",
    "sahwikisource": "php-1.31.0-wmf.24",
    "sawiki": "php-1.31.0-wmf.23",
    "sawikibooks": "php-1.31.0-wmf.24",
    "sawikiquote": "php-1.31.0-wmf.24",
    "sawikisource": "php-1.31.0-wmf.24",
    "sawiktionary": "php-1.31.0-wmf.24",
    "scnwiki": "php-1.31.0-wmf.23",
    "scnwiktionary": "php-1.31.0-wmf.24",
    "scowiki": "php-1.31.0-wmf.23",
    "scwiki": "php-1.31.0-wmf.23",
    "scwiktionary": "php-1.31.0-wmf.24",
    "sdwiki": "php-1.31.0-wmf.23",
    "sdwikinews": "php-1.31.0-wmf.24",
    "sdwiktionary": "php-1.31.0-wmf.24",
    "searchcomwiki": "php-1.31.0-wmf.24",
    "sewiki": "php-1.31.0-wmf.23",
    "sewikibooks": "php-1.31.0-wmf.24",
    "sewikimedia": "php-1.31.0-wmf.24",
    "sgwiki": "php-1.31.0-wmf.23",
    "sgwiktionary": "php-1.31.0-wmf.24",
    "shwiki": "php-1.31.0-wmf.23",
    "shwiktionary": "php-1.31.0-wmf.24",
    "simplewiki": "php-1.31.0-wmf.23",
    "simplewikibooks": "php-1.31.0-wmf.24",
    "simplewikiquote": "php-1.31.0-wmf.24",
    "simplewiktionary": "php-1.31.0-wmf.24",
    "siwiki": "php-1.31.0-wmf.23",
    "siwikibooks": "php-1.31.0-wmf.24",
    "siwiktionary": "php-1.31.0-wmf.24",
    "skwiki": "php-1.31.0-wmf.23",
    "skwikibooks": "php-1.31.0-wmf.24",
    "skwikiquote": "php-1.31.0-wmf.24",
    "skwikisource": "php-1.31.0-wmf.24",
    "skwiktionary": "php-1.31.0-wmf.24",
    "slwiki": "php-1.31.0-wmf.23",
    "slwikibooks": "php-1.31.0-wmf.24",
    "slwikiquote": "php-1.31.0-wmf.24",
    "slwikisource": "php-1.31.0-wmf.24",
    "slwikiversity": "php-1.31.0-wmf.24",
    "slwiktionary": "php-1.31.0-wmf.24",
    "smwiki": "php-1.31.0-wmf.23",
    "smwiktionary": "php-1.31.0-wmf.24",
    "snwiki": "php-1.31.0-wmf.23",
    "snwiktionary": "php-1.31.0-wmf.24",
    "sourceswiki": "php-1.31.0-wmf.24",
    "sowiki": "php-1.31.0-wmf.23",
    "sowiktionary": "php-1.31.0-wmf.24",
    "spcomwiki": "php-1.31.0-wmf.24",
    "specieswiki": "php-1.31.0-wmf.24",
    "sqwiki": "php-1.31.0-wmf.23",
    "sqwikibooks": "php-1.31.0-wmf.24",
    "sqwikinews": "php-1.31.0-wmf.24",
    "sqwikiquote": "php-1.31.0-wmf.24",
    "sqwiktionary": "php-1.31.0-wmf.24",
    "srnwiki": "php-1.31.0-wmf.23",
    "srwiki": "php-1.31.0-wmf.23",
    "srwikibooks": "php-1.31.0-wmf.24",
    "srwikinews": "php-1.31.0-wmf.24",
    "srwikiquote": "php-1.31.0-wmf.24",
    "srwikisource": "php-1.31.0-wmf.24",
    "srwiktionary": "php-1.31.0-wmf.24",
    "sswiki": "php-1.31.0-wmf.23",
    "sswiktionary": "php-1.31.0-wmf.24",
    "stewardwiki": "php-1.31.0-wmf.24",
    "stqwiki": "php-1.31.0-wmf.23",
    "strategywiki": "php-1.31.0-wmf.24",
    "stwiki": "php-1.31.0-wmf.23",
    "stwiktionary": "php-1.31.0-wmf.24",
    "suwiki": "php-1.31.0-wmf.23",
    "suwikibooks": "php-1.31.0-wmf.24",
    "suwikiquote": "php-1.31.0-wmf.24",
    "suwiktionary": "php-1.31.0-wmf.24",
    "svwiki": "php-1.31.0-wmf.23",
    "svwikibooks": "php-1.31.0-wmf.24",
    "svwikinews": "php-1.31.0-wmf.24",
    "svwikiquote": "php-1.31.0-wmf.24",
    "svwikisource": "php-1.31.0-wmf.24",
    "svwikiversity": "php-1.31.0-wmf.24",
    "svwikivoyage": "php-1.31.0-wmf.24",
    "svwiktionary": "php-1.31.0-wmf.24",
    "swwiki": "php-1.31.0-wmf.23",
    "swwikibooks": "php-1.31.0-wmf.24",
    "swwiktionary": "php-1.31.0-wmf.24",
    "szlwiki": "php-1.31.0-wmf.23",
    "tawiki": "php-1.31.0-wmf.23",
    "tawikibooks": "php-1.31.0-wmf.24",
    "tawikinews": "php-1.31.0-wmf.24",
    "tawikiquote": "php-1.31.0-wmf.24",
    "tawikisource": "php-1.31.0-wmf.24",
    "tawiktionary": "php-1.31.0-wmf.24",
    "tcywiki": "php-1.31.0-wmf.23",
    "techconductwiki": "php-1.31.0-wmf.24",
    "tenwiki": "php-1.31.0-wmf.24",
    "test2wiki": "php-1.31.0-wmf.24",
    "testwiki": "php-1.31.0-wmf.24",
    "testwikidatawiki": "php-1.31.0-wmf.24",
    "tetwiki": "php-1.31.0-wmf.23",
    "tewiki": "php-1.31.0-wmf.23",
    "tewikibooks": "php-1.31.0-wmf.24",
    "tewikiquote": "php-1.31.0-wmf.24",
    "tewikisource": "php-1.31.0-wmf.24",
    "tewiktionary": "php-1.31.0-wmf.24",
    "tgwiki": "php-1.31.0-wmf.23",
    "tgwikibooks": "php-1.31.0-wmf.24",
    "tgwiktionary": "php-1.31.0-wmf.24",
    "thwiki": "php-1.31.0-wmf.23",
    "thwikibooks": "php-1.31.0-wmf.24",
    "thwikinews": "php-1.31.0-wmf.24",
    "thwikiquote": "php-1.31.0-wmf.24",
    "thwikisource": "php-1.31.0-wmf.24",
    "thwiktionary": "php-1.31.0-wmf.24",
    "tiwiki": "php-1.31.0-wmf.23",
    "tiwiktionary": "php-1.31.0-wmf.24",
    "tkwiki": "php-1.31.0-wmf.23",
    "tkwikibooks": "php-1.31.0-wmf.24",
    "tkwikiquote": "php-1.31.0-wmf.24",
    "tkwiktionary": "php-1.31.0-wmf.24",
    "tlwiki": "php-1.31.0-wmf.23",
    "tlwikibooks": "php-1.31.0-wmf.24",
    "tlwiktionary": "php-1.31.0-wmf.24",
    "tnwiki": "php-1.31.0-wmf.23",
    "tnwiktionary": "php-1.31.0-wmf.24",
    "towiki": "php-1.31.0-wmf.23",
    "towiktionary": "php-1.31.0-wmf.24",
    "tpiwiki": "php-1.31.0-wmf.23",
    "tpiwiktionary": "php-1.31.0-wmf.24",
    "transitionteamwiki": "php-1.31.0-wmf.24",
    "trwiki": "php-1.31.0-wmf.23",
    "trwikibooks": "php-1.31.0-wmf.24",
    "trwikimedia": "php-1.31.0-wmf.24",
    "trwikinews": "php-1.31.0-wmf.24",
    "trwikiquote": "php-1.31.0-wmf.24",
    "trwikisource": "php-1.31.0-wmf.24",
    "trwiktionary": "php-1.31.0-wmf.24",
    "tswiki": "php-1.31.0-wmf.23",
    "tswiktionary": "php-1.31.0-wmf.24",
    "ttwiki": "php-1.31.0-wmf.23",
    "ttwikibooks": "php-1.31.0-wmf.24",
    "ttwikiquote": "php-1.31.0-wmf.24",
    "ttwiktionary": "php-1.31.0-wmf.24",
    "tumwiki": "php-1.31.0-wmf.23",
    "twwiki": "php-1.31.0-wmf.23",
    "twwiktionary": "php-1.31.0-wmf.24",
    "tyvwiki": "php-1.31.0-wmf.23",
    "tywiki": "php-1.31.0-wmf.23",
    "uawikimedia": "php-1.31.0-wmf.24",
    "udmwiki": "php-1.31.0-wmf.23",
    "ugwiki": "php-1.31.0-wmf.23",
    "ugwikibooks": "php-1.31.0-wmf.24",
    "ugwikiquote": "php-1.31.0-wmf.24",
    "ugwiktionary": "php-1.31.0-wmf.24",
    "ukwiki": "php-1.31.0-wmf.23",
    "ukwikibooks": "php-1.31.0-wmf.24",
    "ukwikinews": "php-1.31.0-wmf.24",
    "ukwikiquote": "php-1.31.0-wmf.24",
    "ukwikisource": "php-1.31.0-wmf.24",
    "ukwikivoyage": "php-1.31.0-wmf.24",
    "ukwiktionary": "php-1.31.0-wmf.24",
    "urwiki": "php-1.31.0-wmf.23",
    "urwikibooks": "php-1.31.0-wmf.24",
    "urwikiquote": "php-1.31.0-wmf.24",
    "urwiktionary": "php-1.31.0-wmf.24",
    "usabilitywiki": "php-1.31.0-wmf.24",
    "uzwiki": "php-1.31.0-wmf.23",
    "uzwikibooks": "php-1.31.0-wmf.24",
    "uzwikiquote": "php-1.31.0-wmf.24",
    "uzwiktionary": "php-1.31.0-wmf.24",
    "vecwiki": "php-1.31.0-wmf.23",
    "vecwikisource": "php-1.31.0-wmf.24",
    "vecwiktionary": "php-1.31.0-wmf.24",
    "vepwiki": "php-1.31.0-wmf.23",
    "vewiki": "php-1.31.0-wmf.23",
    "viwiki": "php-1.31.0-wmf.23",
    "viwikibooks": "php-1.31.0-wmf.24",
    "viwikiquote": "php-1.31.0-wmf.24",
    "viwikisource": "php-1.31.0-wmf.24",
    "viwikivoyage": "php-1.31.0-wmf.24",
    "viwiktionary": "php-1.31.0-wmf.24",
    "vlswiki": "php-1.31.0-wmf.23",
    "votewiki": "php-1.31.0-wmf.24",
    "vowiki": "php-1.31.0-wmf.23",
    "vowikibooks": "php-1.31.0-wmf.24",
    "vowikiquote": "php-1.31.0-wmf.24",
    "vowiktionary": "php-1.31.0-wmf.24",
    "warwiki": "php-1.31.0-wmf.23",
    "wawiki": "php-1.31.0-wmf.23",
    "wawikibooks": "php-1.31.0-wmf.24",
    "wawiktionary": "php-1.31.0-wmf.24",
    "wbwikimedia": "php-1.31.0-wmf.24",
    "wg_enwiki": "php-1.31.0-wmf.23",
    "wikidatawiki": "php-1.31.0-wmf.24",
    "wikimania2005wiki": "php-1.31.0-wmf.24",
    "wikimania2006wiki": "php-1.31.0-wmf.24",
    "wikimania2007wiki": "php-1.31.0-wmf.24",
    "wikimania2008wiki": "php-1.31.0-wmf.24",
    "wikimania2009wiki": "php-1.31.0-wmf.24",
    "wikimania2010wiki": "php-1.31.0-wmf.24",
    "wikimania2011wiki": "php-1.31.0-wmf.24",
    "wikimania2012wiki": "php-1.31.0-wmf.24",
    "wikimania2013wiki": "php-1.31.0-wmf.24",
    "wikimania2014wiki": "php-1.31.0-wmf.24",
    "wikimania2015wiki": "php-1.31.0-wmf.24",
    "wikimania2016wiki": "php-1.31.0-wmf.24",
    "wikimania2017wiki": "php-1.31.0-wmf.24",
    "wikimania2018wiki": "php-1.31.0-wmf.24",
    "wikimaniateamwiki": "php-1.31.0-wmf.24",
    "wowiki": "php-1.31.0-wmf.23",
    "wowikiquote": "php-1.31.0-wmf.24",
    "wowiktionary": "php-1.31.0-wmf.24",
    "wuuwiki": "php-1.31.0-wmf.23",
    "xalwiki": "php-1.31.0-wmf.23",
    "xhwiki": "php-1.31.0-wmf.23",
    "xhwikibooks": "php-1.31.0-wmf.24",
    "xhwiktionary": "php-1.31.0-wmf.24",
    "xmfwiki": "php-1.31.0-wmf.23",
    "yiwiki": "php-1.31.0-wmf.23",
    "yiwikisource": "php-1.31.0-wmf.24",
    "yiwiktionary": "php-1.31.0-wmf.24",
    "yowiki": "php-1.31.0-wmf.23",
    "yowikibooks": "php-1.31.0-wmf.24",
    "yowiktionary": "php-1.31.0-wmf.24",
    "zawiki": "php-1.31.0-wmf.23",
    "zawikibooks": "php-1.31.0-wmf.24",
    "zawikiquote": "php-1.31.0-wmf.24",
    "zawiktionary": "php-1.31.0-wmf.24",
    "zeawiki": "php-1.31.0-wmf.23",
    "zerowiki": "php-1.31.0-wmf.24",
    "zh_classicalwiki": "php-1.31.0-wmf.23",
    "zh_min_nanwiki": "php-1.31.0-wmf.23",
    "zh_min_nanwikibooks": "php-1.31.0-wmf.24",
    "zh_min_nanwikiquote": "php-1.31.0-wmf.24",
    "zh_min_nanwikisource": "php-1.31.0-wmf.24",
    "zh_min_nanwiktionary": "php-1.31.0-wmf.24",
    "zh_yuewiki": "php-1.31.0-wmf.23",
    "zhwiki": "php-1.31.0-wmf.23",
    "zhwikibooks": "php-1.31.0-wmf.24",
    "zhwikinews": "php-1.31.0-wmf.24",
    "zhwikiquote": "php-1.31.0-wmf.24",
    "zhwikisource": "php-1.31.0-wmf.24",
    "zhwikivoyage": "php-1.31.0-wmf.24",
    "zhwiktionary": "php-1.31.0-wmf.24",
    "zuwiki": "php-1.31.0-wmf.23",
    "zuwikibooks": "php-1.31.0-wmf.24",
    "zuwiktionary": "php-1.31.0-wmf.24"
}
